mdfr-0.6.3.dist-info/METADATA
mdfr-0.6.3.dist-info/WHEEL
mdfr-0.6.3.dist-info/licenses/LICENSE
mdfr/__init__.py
mdfr/mdfr.cpython-311-darwin.so
mdfr-0.6.3.dist-info/RECORD
