Metadata-Version: 2.4
Name: mdfr
Version: 0.6.3
Requires-Dist: numpy>=1.23
Requires-Dist: polars>=0.13
Requires-Dist: matplotlib>=3.5
License-File: LICENSE
Summary: A package for reading and writing MDF files
Author: ratal <ratal@ratal.org>
Author-email: ratal <ratal@ratal.org>
License: GPL-3.0
Requires-Python: >=3.7
Project-URL: Source Code, https://github.com/ratal/mdfr/
